obwsc/__init__.py
obwsc/log.py
obwsc/options.py
obwsc/cli/__init__.py
obwsc/cli/obws_command.py
obwsc/commands/__init__.py
obwsc/commands/event_based_command.py
obwsc/commands/pause_record.py
obwsc/commands/resume_record.py
obwsc/commands/set_current_profile.py
obwsc/commands/set_current_scene_collection.py
obwsc/commands/start_record.py
obwsc/commands/stop_record.py
obwsc/commands/switch_profile_and_scene_collection.py
obws_commands-0.0.6.dist-info/LICENSE
obws_commands-0.0.6.dist-info/METADATA
obws_commands-0.0.6.dist-info/WHEEL
obws_commands-0.0.6.dist-info/entry_points.txt
obws_commands-0.0.6.dist-info/top_level.txt
obws_commands-0.0.6.dist-info/RECORD
