Metadata-Version: 2.1
Name: obws-commands
Version: 0.0.6
Summary: An event-based command line interface for OBS Websocket
Author-email: Dennis Sitelew <yowidin@gmail.com>
Project-URL: homepage, https://github.com/yowidin/obws-commands
Project-URL: bugtrack, https://github.com/yowidin/obws-commands/issues
Classifier: Programming Language :: Python :: 3
Classifier: License :: OSI Approved :: MIT License
Requires-Python: >=3.7
License-File: LICENSE
Requires-Dist: obsws-python~=1.7.0
Requires-Dist: toml~=0.10.2
